django_mptt_simple_listfilters/__init__.py
django_mptt_simple_listfilters/admin.py
django_mptt_simple_listfilters/apps.py
django_mptt_simple_listfilters/filters.py
django_mptt_simple_listfilters/models.py
django_mptt_simple_listfilters/tests.py
django_mptt_simple_listfilters/views.py
django_mptt_simple_listfilters/migrations/__init__.py
django_mptt_simple_listfilters-0.1.2.dist-info/licenses/LICENSE
django_mptt_simple_listfilters-0.1.2.dist-info/METADATA
django_mptt_simple_listfilters-0.1.2.dist-info/WHEEL
django_mptt_simple_listfilters-0.1.2.dist-info/top_level.txt
django_mptt_simple_listfilters-0.1.2.dist-info/RECORD
